masscube/__init__.py
masscube/alignment.py
masscube/annotation.py
masscube/classifier_builder.py
masscube/feature_detection.py
masscube/feature_evaluation.py
masscube/feature_grouping.py
masscube/mzpkl.py
masscube/network.py
masscube/normalization.py
masscube/params.py
masscube/raw_data_utils.py
masscube/stats.py
masscube/utils_functions.py
masscube/visualization.py
masscube/workflows.py
masscube-1.2.4.dist-info/LICENSE
masscube-1.2.4.dist-info/METADATA
masscube-1.2.4.dist-info/WHEEL
masscube-1.2.4.dist-info/entry_points.txt
masscube-1.2.4.dist-info/top_level.txt
masscube-1.2.4.dist-info/RECORD
