Metadata-Version: 2.1
Name: masscube
Version: 1.2.4
Summary: Accurate and fast data processing for metabolomics
Author-email: Huaxu Yu <yhxchem@outlook.com>
Maintainer-email: Huaxu Yu <yhxchem@outlook.com>
License: CC BY-NC 4.0
Project-URL: Homepage, https://github.com/huaxuyu/masscube
Classifier: Programming Language :: Python :: 3
Classifier: License :: Other/Proprietary License
Classifier: Operating System :: OS Independent
Requires-Python: >=3.8
License-File: LICENSE
Requires-Dist: numpy>=1.24
Requires-Dist: pandas>=2.2.1
Requires-Dist: pyteomics==4.6.3
Requires-Dist: scipy>=1.10.1
Requires-Dist: tqdm>=4.66.1
Requires-Dist: lxml>=4.9.3
Requires-Dist: matplotlib>=3.8.2
Requires-Dist: ms-entropy==1.3.4
Requires-Dist: scikit-learn>=1.3.2
Requires-Dist: statsmodels>=0.14.2
Requires-Dist: umap-learn>=0.5.7
